neonutilities/__init__.py
neonutilities/aop_download.py
neonutilities/citation.py
neonutilities/files_by_uri.py
neonutilities/get_issue_log.py
neonutilities/read_table_neon.py
neonutilities/tabular_download.py
neonutilities/unzip_and_stack.py
neonutilities/__resources__/added_fields.csv
neonutilities/__resources__/chem_bundles.csv
neonutilities/__resources__/frame_file_variables.csv
neonutilities/__resources__/neon_field_site_metadata_20250214.csv
neonutilities/__resources__/other_bundles.csv
neonutilities/__resources__/science_review_variables.csv
neonutilities/__resources__/sensor_positions_variables.csv
neonutilities/__resources__/sensor_positions_variables_mapping.csv
neonutilities/__resources__/shared_aquatic.csv
neonutilities/__resources__/shared_flights.csv
neonutilities/helper_mods/__init__.py
neonutilities/helper_mods/api_helpers.py
neonutilities/helper_mods/metadata_helpers.py
neonutilities-1.1.0.dist-info/licenses/LICENSE
neonutilities-1.1.0.dist-info/METADATA
neonutilities-1.1.0.dist-info/WHEEL
neonutilities-1.1.0.dist-info/top_level.txt
neonutilities-1.1.0.dist-info/RECORD
