Metadata-Version: 2.4
Name: neonutilities
Version: 1.1.0
Summary: A package for accessing and wrangling data generated and published by the National Ecological Observatory Network.
Author-email: Claire Lunch <clunch@battelleecology.org>, Bridget Hass <bhass@battelleecology.org>, Zachary Nickerson <nickerson@battelleecology.org>
License:                     GNU AFFERO GENERAL PUBLIC LICENSE
Project-URL: Homepage, https://github.com/NEONScience/NEON-utilities-python
Project-URL: Documentation, https://neon-utilities-python.readthedocs.io/en/latest/
Project-URL: Repository, https://github.com/NEONScience/NEON-utilities-python
Project-URL: Issues, https://github.com/NEONScience/NEON-utilities-python/issues
Project-URL: Changelog, https://github.com/NEONScience/NEON-utilities-python/blob/main/CHANGELOG.md
Requires-Python: >=3.9
License-File: LICENSE
Requires-Dist: importlib-resources
Requires-Dist: pandas
Requires-Dist: parameterized
Requires-Dist: pyarrow
Requires-Dist: pyproj
Requires-Dist: requests
Requires-Dist: tqdm
Dynamic: license-file
